MANIFEST.in
README.rst
setup.py
petlink/__init__.py
petlink/petlink.py
petlink/petlink32_c.c
petlink.egg-info/PKG-INFO
petlink.egg-info/SOURCES.txt
petlink.egg-info/dependency_links.txt
petlink.egg-info/requires.txt
petlink.egg-info/top_level.txt
petlink/examples/__init__.py
petlink/tests/__init__.py
petlink/tests/test_all.py