Metadata-Version: 1.1
Name: petlink
Version: 0.3.2
Summary: Decode and encode PETlink streams.
Home-page: http://occiput.scienceontheweb.net/
Author: Stefano Pedemonte
Author-email: stefano.pedemonte@gmail.com
License: LICENSE.txt
Platform: UNKNOWN
Classifier: Programming Language :: Python
Classifier: Development Status :: 4 - Beta
Classifier: Environment :: Other Environment
Classifier: Intended Audience :: Science/Research
Classifier: License :: OSI Approved :: BSD License
Classifier: Operating System :: OS Independent
Classifier: Topic :: Scientific/Engineering :: Medical Science Apps.
Classifier: Topic :: Scientific/Engineering :: Mathematics
